{"v":"5.12.2","fr":8,"ip":0,"op":25,"w":256,"h":211,"nm":"pulpito","ddd":0,"assets":[],"layers":[{"ddd":0,"ind":1,"ty":4,"nm":"tentaculo8 contornos","sr":1,"ks":{"o":{"a":0,"k":100,"ix":11},"r":{"a":1,"k":[{"i":{"x":[0.667],"y":[1]},"o":{"x":[0.333],"y":[0]},"t":0,"s":[0]},{"i":{"x":[0.667],"y":[1]},"o":{"x":[0.333],"y":[0]},"t":6,"s":[13]},{"i":{"x":[0.667],"y":[1]},"o":{"x":[0.333],"y":[0]},"t":12,"s":[-8]},{"i":{"x":[0.667],"y":[1]},"o":{"x":[0.333],"y":[0]},"t":18,"s":[13]},{"t":24,"s":[0]}],"ix":10},"p":{"a":0,"k":[130.564,136.876,0],"ix":2,"l":2},"a":{"a":0,"k":[0.414,2.375,0],"ix":1,"l":2},"s":{"a":0,"k":[100,100,100],"ix":6,"l":2}},"ao":0,"shapes":[{"ty":"gr","it":[{"ind":0,"ty":"sh","ix":1,"ks":{"a":0,"k":{"i":[[4.741,2.479],[-1.923,-8.575],[-0.619,-2.515],[-5.533,0.032],[-2.579,0.321],[1.736,-9.821],[0.494,-1.461],[0.435,1.681],[5.904,-1.675],[2.266,-0.621],[2.134,9.877],[1.499,3.889]],"o":[[9.26,-0.815],[0.568,2.531],[1.311,5.334],[2.592,-0.015],[11.769,-1.461],[-0.154,0.868],[-0.492,-2.324],[-1.533,-5.919],[-2.26,0.641],[-10.086,2.766],[-0.884,-4.094],[-1.642,-4.262]],"v":[[-27.164,-22.81],[-7.974,-10.061],[-6.575,-2.4],[4.805,6.445],[12.576,5.785],[25.428,20.471],[24.381,23.624],[23.158,17.902],[12.687,11.947],[5.916,13.902],[-15.229,0.104],[-18.494,-12.032]],"c":true},"ix":2},"nm":"Trazado 1","mn":"ADBE Vector Shape - Group","hd":false},{"ty":"fl","c":{"a":0,"k":[0,0,0,1],"ix":4},"o":{"a":0,"k":100,"ix":5},"r":1,"bm":0,"nm":"Relleno 1","mn":"ADBE Vector Graphic - Fill","hd":false},{"ty":"tr","p":{"a":0,"k":[27.414,23.875],"ix":2},"a":{"a":0,"k":[0,0],"ix":1},"s":{"a":0,"k":[100,100],"ix":3},"r":{"a":0,"k":0,"ix":6},"o":{"a":0,"k":100,"ix":7},"sk":{"a":0,"k":0,"ix":4},"sa":{"a":0,"k":0,"ix":5},"nm":"Transformar"}],"nm":"Grupo 1","np":2,"cix":2,"bm":0,"ix":1,"mn":"ADBE Vector Group","hd":false}],"ip":0,"op":25,"st":0,"ct":1,"bm":0},{"ddd":0,"ind":2,"ty":4,"nm":"tentaculo7 contornos","sr":1,"ks":{"o":{"a":0,"k":100,"ix":11},"r":{"a":1,"k":[{"i":{"x":[0.667],"y":[1]},"o":{"x":[0.333],"y":[0]},"t":0,"s":[0]},{"i":{"x":[0.667],"y":[1]},"o":{"x":[0.333],"y":[0]},"t":6,"s":[13]},{"i":{"x":[0.667],"y":[1]},"o":{"x":[0.333],"y":[0]},"t":12,"s":[-8]},{"i":{"x":[0.667],"y":[1]},"o":{"x":[0.333],"y":[0]},"t":18,"s":[13]},{"t":24,"s":[0]}],"ix":10},"p":{"a":0,"k":[124.059,136.266,0],"ix":2,"l":2},"a":{"a":0,"k":[53.826,1.116,0],"ix":1,"l":2},"s":{"a":0,"k":[100,100,100],"ix":6,"l":2}},"ao":0,"shapes":[{"ty":"gr","it":[{"ind":0,"ty":"sh","ix":1,"ks":{"a":0,"k":{"i":[[-5.757,0.038],[1.595,-7.778],[2.999,-3.243],[7.106,2.32],[1.458,0.392],[1.588,-6.759],[0.561,-1.313],[-1.313,3.87],[-3.498,0.152],[-2.589,-0.254],[-3.655,2.198],[-0.432,4],[-3.166,3.597]],"o":[[-7.041,5.081],[-0.878,4.286],[-5.212,5.637],[-1.436,-0.469],[-6.673,-1.792],[-0.317,1.351],[-1.257,-3.863],[1.128,-3.325],[2.585,-0.113],[3.965,0.39],[3.537,-2.128],[0.492,-4.557],[4.02,-4.566]],"v":[[26.576,-22.865],[15.725,-2.43],[10.689,9.165],[-8.007,13.49],[-12.344,12.174],[-23.432,18.857],[-24.652,22.865],[-25.263,11.23],[-18.036,5.859],[-10.25,6.32],[1.285,4.868],[6.947,-4.428],[11.479,-17.018]],"c":true},"ix":2},"nm":"Trazado 1","mn":"ADBE Vector Shape - Group","hd":false},{"ty":"fl","c":{"a":0,"k":[0,0,0,1],"ix":4},"o":{"a":0,"k":100,"ix":5},"r":1,"bm":0,"nm":"Relleno 1","mn":"ADBE Vector Graphic - Fill","hd":false},{"ty":"tr","p":{"a":0,"k":[26.826,23.116],"ix":2},"a":{"a":0,"k":[0,0],"ix":1},"s":{"a":0,"k":[100,100],"ix":3},"r":{"a":0,"k":0,"ix":6},"o":{"a":0,"k":100,"ix":7},"sk":{"a":0,"k":0,"ix":4},"sa":{"a":0,"k":0,"ix":5},"nm":"Transformar"}],"nm":"Grupo 1","np":2,"cix":2,"bm":0,"ix":1,"mn":"ADBE Vector Group","hd":false}],"ip":0,"op":25,"st":0,"ct":1,"bm":0},{"ddd":0,"ind":3,"ty":4,"nm":"tentaculo6 contornos","sr":1,"ks":{"o":{"a":0,"k":100,"ix":11},"r":{"a":1,"k":[{"i":{"x":[0.667],"y":[1]},"o":{"x":[0.333],"y":[0]},"t":0,"s":[0]},{"i":{"x":[0.667],"y":[1]},"o":{"x":[0.333],"y":[0]},"t":6,"s":[8]},{"i":{"x":[0.667],"y":[1]},"o":{"x":[0.333],"y":[0]},"t":12,"s":[-10]},{"i":{"x":[0.667],"y":[1]},"o":{"x":[0.333],"y":[0]},"t":18,"s":[8]},{"t":24,"s":[0]}],"ix":10},"p":{"a":0,"k":[143.563,135.353,0],"ix":2,"l":2},"a":{"a":0,"k":[0.864,2.024,0],"ix":1,"l":2},"s":{"a":0,"k":[100,100,100],"ix":6,"l":2}},"ao":0,"shapes":[{"ty":"gr","it":[{"ind":0,"ty":"sh","ix":1,"ks":{"a":0,"k":{"i":[[8.056,3.238],[-0.863,0.072],[-3.669,3.899],[0.905,5.016],[3.415,0.366],[4.289,-1.469],[10.138,4.29],[5.547,4.895],[2.183,2.809],[-1.092,-0.431],[-7.115,-2.483],[-9.874,1.867],[-5.705,0.883],[-0.81,-9.087],[6.492,-5.455]],"o":[[0.856,-0.15],[5.161,-0.432],[3.662,-3.89],[-0.505,-2.8],[-4.513,-0.483],[-10.316,3.531],[-6.887,-2.915],[-2.504,-2.209],[1.13,0.334],[7.02,2.762],[9.623,3.359],[5.681,-1.075],[8.976,-1.39],[0.758,8.505],[-6.888,5.787]],"v":[[12.379,20.156],[14.949,19.715],[28.515,13.947],[31.99,0.314],[25.033,-5.006],[11.906,-3.249],[-18.868,-3.924],[-37.013,-16.446],[-44.114,-23.775],[-40.728,-22.758],[-19.675,-14.465],[9.736,-13.303],[26.701,-16.924],[43.356,-3.182],[35.184,17.988]],"c":true},"ix":2},"nm":"Trazado 1","mn":"ADBE Vector Shape - Group","hd":false},{"ty":"fl","c":{"a":0,"k":[0,0,0,1],"ix":4},"o":{"a":0,"k":100,"ix":5},"r":1,"bm":0,"nm":"Relleno 1","mn":"ADBE Vector Graphic - Fill","hd":false},{"ty":"tr","p":{"a":0,"k":[44.364,24.024],"ix":2},"a":{"a":0,"k":[0,0],"ix":1},"s":{"a":0,"k":[100,100],"ix":3},"r":{"a":0,"k":0,"ix":6},"o":{"a":0,"k":100,"ix":7},"sk":{"a":0,"k":0,"ix":4},"sa":{"a":0,"k":0,"ix":5},"nm":"Transformar"}],"nm":"Grupo 1","np":2,"cix":2,"bm":0,"ix":1,"mn":"ADBE Vector Group","hd":false}],"ip":0,"op":25,"st":0,"ct":1,"bm":0},{"ddd":0,"ind":4,"ty":4,"nm":"tentaculo5 contornos","sr":1,"ks":{"o":{"a":0,"k":100,"ix":11},"r":{"a":1,"k":[{"i":{"x":[0.667],"y":[1]},"o":{"x":[0.333],"y":[0]},"t":0,"s":[0]},{"i":{"x":[0.667],"y":[1]},"o":{"x":[0.333],"y":[0]},"t":6,"s":[8]},{"i":{"x":[0.667],"y":[1]},"o":{"x":[0.333],"y":[0]},"t":12,"s":[-10]},{"i":{"x":[0.667],"y":[1]},"o":{"x":[0.333],"y":[0]},"t":18,"s":[8]},{"t":24,"s":[0]}],"ix":10},"p":{"a":0,"k":[113.178,134.593,0],"ix":2,"l":2},"a":{"a":0,"k":[89.951,1.361,0],"ix":1,"l":2},"s":{"a":0,"k":[100,100,100],"ix":6,"l":2}},"ao":0,"shapes":[{"ty":"gr","it":[{"ind":0,"ty":"sh","ix":1,"ks":{"a":0,"k":{"i":[[-0.093,-0.234],[11.288,-3.986],[9.207,2.787],[3.794,0.179],[-2.092,-7.659],[-6.414,-1.332],[-2.618,-0.369],[5.281,13.276],[-1.55,5.373],[-7.197,-0.982],[-4.322,-0.989],[-11.79,4.238],[-6.366,2.586],[-1.087,0.36]],"o":[[-8.525,7.924],[-9.037,3.191],[-3.653,-1.106],[-8.726,-0.413],[1.811,6.63],[2.011,0.418],[-11.921,5.166],[-2.121,-5.332],[1.866,-6.471],[4.377,0.598],[12.014,2.75],[6.46,-2.322],[1.059,-0.43],[0.093,0.234]],"v":[[44.201,-23.91],[16.094,-3.617],[-11.402,-3.65],[-22.693,-5.785],[-31.926,7.311],[-18.65,18.481],[-11.962,19.445],[-42.079,7.818],[-42.547,-8.23],[-27.228,-17.732],[-14.24,-14.885],[21.568,-15.764],[40.663,-23.521],[43.921,-24.611]],"c":true},"ix":2},"nm":"Trazado 1","mn":"ADBE Vector Shape - Group","hd":false},{"ty":"fl","c":{"a":0,"k":[0,0,0,1],"ix":4},"o":{"a":0,"k":100,"ix":5},"r":1,"bm":0,"nm":"Relleno 1","mn":"ADBE Vector Graphic - Fill","hd":false},{"ty":"tr","p":{"a":0,"k":[44.451,24.861],"ix":2},"a":{"a":0,"k":[0,0],"ix":1},"s":{"a":0,"k":[100,100],"ix":3},"r":{"a":0,"k":0,"ix":6},"o":{"a":0,"k":100,"ix":7},"sk":{"a":0,"k":0,"ix":4},"sa":{"a":0,"k":0,"ix":5},"nm":"Transformar"}],"nm":"Grupo 1","np":2,"cix":2,"bm":0,"ix":1,"mn":"ADBE Vector Group","hd":false}],"ip":0,"op":25,"st":0,"ct":1,"bm":0},{"ddd":0,"ind":5,"ty":4,"nm":"tentaculo4 contornos","sr":1,"ks":{"o":{"a":0,"k":100,"ix":11},"r":{"a":1,"k":[{"i":{"x":[0.667],"y":[1]},"o":{"x":[0.333],"y":[0]},"t":0,"s":[0]},{"i":{"x":[0.667],"y":[1]},"o":{"x":[0.333],"y":[0]},"t":6,"s":[7]},{"i":{"x":[0.667],"y":[1]},"o":{"x":[0.333],"y":[0]},"t":12,"s":[-6]},{"i":{"x":[0.667],"y":[1]},"o":{"x":[0.333],"y":[0]},"t":18,"s":[7]},{"t":24,"s":[0]}],"ix":10},"p":{"a":0,"k":[99.916,136.158,0],"ix":2,"l":2},"a":{"a":0,"k":[82.245,58.495,0],"ix":1,"l":2},"s":{"a":0,"k":[100,100,100],"ix":6,"l":2}},"ao":0,"shapes":[{"ty":"gr","it":[{"ind":0,"ty":"sh","ix":1,"ks":{"a":0,"k":{"i":[[-0.057,-0.195],[3.218,-0.743],[5.905,-0.717],[5.41,7.215],[0.197,5.918],[0.429,5.342],[0.773,2.028],[4.936,0.226],[1.881,-3.873],[1.321,-3.781],[0.233,-0.685],[0.037,0.224],[-10.444,4.7],[-4.621,-6.522],[-0.479,-4.302],[-5.746,-6.337],[-9.852,-0.86],[-3.945,0]],"o":[[-3.13,1.12],[-5.803,1.34],[-8.482,1.029],[-3.598,-4.798],[-0.178,-5.362],[-0.17,-2.112],[-1.883,-4.946],[-4.664,-0.214],[-1.737,3.579],[-0.156,0.447],[-0.407,-0.351],[-1.839,-10.954],[6.988,-3.145],[2.519,3.555],[0.883,7.931],[6.704,7.394],[3.915,0.342],[0.057,0.195]],"v":[[41.995,24.628],[32.589,27.92],[15.02,31.216],[-6.529,23.059],[-11.596,6.704],[-12.245,-9.374],[-14.145,-15.594],[-24.98,-22.728],[-34.734,-16.357],[-38.788,-5.057],[-39.327,-3.475],[-40.157,-4.215],[-28.222,-29.1],[-6.727,-22.267],[-2.741,-10.556],[5.221,11.55],[29.995,23.987],[41.826,24.043]],"c":true},"ix":2},"nm":"Trazado 1","mn":"ADBE Vector Shape - Group","hd":false},{"ty":"fl","c":{"a":0,"k":[0,0,0,1],"ix":4},"o":{"a":0,"k":100,"ix":5},"r":1,"bm":0,"nm":"Relleno 1","mn":"ADBE Vector Graphic - Fill","hd":false},{"ty":"tr","p":{"a":0,"k":[42.245,32.495],"ix":2},"a":{"a":0,"k":[0,0],"ix":1},"s":{"a":0,"k":[100,100],"ix":3},"r":{"a":0,"k":0,"ix":6},"o":{"a":0,"k":100,"ix":7},"sk":{"a":0,"k":0,"ix":4},"sa":{"a":0,"k":0,"ix":5},"nm":"Transformar"}],"nm":"Grupo 1","np":2,"cix":2,"bm":0,"ix":1,"mn":"ADBE Vector Group","hd":false}],"ip":0,"op":25,"st":0,"ct":1,"bm":0},{"ddd":0,"ind":6,"ty":4,"nm":"tentaculo3 contornos","sr":1,"ks":{"o":{"a":0,"k":100,"ix":11},"r":{"a":1,"k":[{"i":{"x":[0.667],"y":[1]},"o":{"x":[0.333],"y":[0]},"t":0,"s":[0]},{"i":{"x":[0.667],"y":[1]},"o":{"x":[0.333],"y":[0]},"t":6,"s":[7]},{"i":{"x":[0.667],"y":[1]},"o":{"x":[0.333],"y":[0]},"t":12,"s":[-6]},{"i":{"x":[0.667],"y":[1]},"o":{"x":[0.333],"y":[0]},"t":18,"s":[7]},{"t":24,"s":[0]}],"ix":10},"p":{"a":0,"k":[155.365,134.543,0],"ix":2,"l":2},"a":{"a":0,"k":[2.964,57.347,0],"ix":1,"l":2},"s":{"a":0,"k":[100,100,100],"ix":6,"l":2}},"ao":0,"shapes":[{"ty":"gr","it":[{"ind":0,"ty":"sh","ix":1,"ks":{"a":0,"k":{"i":[[0.281,0.323],[-3.562,0.216],[-6.33,10.868],[-1.38,5.331],[-1.346,3.155],[-8.234,-3.8],[0.861,-8.825],[0.15,-1.462],[0.214,-0.037],[0.218,0.89],[3.031,3.791],[2.766,-6.57],[-0.4,-5.846],[3.436,-6.333],[7.863,-0.097],[10.065,4.053]],"o":[[3.733,0],[12.6,-0.765],[2.681,-4.603],[0.875,-3.377],[3.807,-8.921],[7.913,3.653],[-0.143,1.463],[-0.213,0.037],[-0.278,-0.876],[-1.123,-4.595],[-5.083,-6.356],[-2.259,5.366],[0.476,6.939],[-3.901,7.193],[-10.85,0.134],[-0.262,-0.106]],"v":[[-41.714,24.708],[-30.833,24.674],[-1.744,7.492],[2.845,-8.322],[5.203,-18.507],[29.103,-28.298],[40.853,-7.513],[40.403,-3.127],[39.763,-3.016],[38.938,-5.644],[33.247,-18.385],[14.753,-15.7],[11.744,0.98],[8.464,21.109],[-9.641,31.964],[-41.01,25.493]],"c":true},"ix":2},"nm":"Trazado 1","mn":"ADBE Vector Shape - Group","hd":false},{"ty":"fl","c":{"a":0,"k":[0,0,0,1],"ix":4},"o":{"a":0,"k":100,"ix":5},"r":1,"bm":0,"nm":"Relleno 1","mn":"ADBE Vector Graphic - Fill","hd":false},{"ty":"tr","p":{"a":0,"k":[41.964,32.348],"ix":2},"a":{"a":0,"k":[0,0],"ix":1},"s":{"a":0,"k":[100,100],"ix":3},"r":{"a":0,"k":0,"ix":6},"o":{"a":0,"k":100,"ix":7},"sk":{"a":0,"k":0,"ix":4},"sa":{"a":0,"k":0,"ix":5},"nm":"Transformar"}],"nm":"Grupo 1","np":2,"cix":2,"bm":0,"ix":1,"mn":"ADBE Vector Group","hd":false}],"ip":0,"op":25,"st":0,"ct":1,"bm":0},{"ddd":0,"ind":7,"ty":4,"nm":"tentaculo2 contornos","sr":1,"ks":{"o":{"a":0,"k":100,"ix":11},"r":{"a":1,"k":[{"i":{"x":[0.667],"y":[1]},"o":{"x":[0.333],"y":[0]},"t":0,"s":[0]},{"i":{"x":[0.667],"y":[1]},"o":{"x":[0.333],"y":[0]},"t":6,"s":[-5]},{"i":{"x":[0.667],"y":[1]},"o":{"x":[0.333],"y":[0]},"t":12,"s":[0]},{"i":{"x":[0.667],"y":[1]},"o":{"x":[0.333],"y":[0]},"t":18,"s":[-5]},{"t":24,"s":[0]}],"ix":10},"p":{"a":0,"k":[118.201,127.457,0],"ix":2,"l":2},"a":{"a":0,"k":[65.762,109.412,0],"ix":1,"l":2},"s":{"a":0,"k":[100,105.176,100],"ix":6,"l":2}},"ao":0,"shapes":[{"ty":"gr","it":[{"ind":0,"ty":"sh","ix":1,"ks":{"a":0,"k":{"i":[[-0.022,-0.278],[2.636,-0.584],[10.063,6.221],[0.531,10.545],[-6.255,9.052],[0.626,11.122],[9.097,-0.562],[3.182,-3.359],[1.233,-1.434],[-5.848,1.9],[-3.337,-15.008],[4.572,-12.039],[-3.109,-10.916],[-6.033,-3.008],[-4.765,-0.265],[-1.267,-0.169]],"o":[[-2.595,0.772],[-11.575,2.564],[-9.006,-5.568],[-0.569,-11.303],[6.121,-8.859],[-0.612,-10.889],[-4.818,0.298],[-1.144,1.207],[0.205,-5.851],[12.385,-4.025],[2.885,12.97],[-4.039,10.637],[1.857,6.521],[4.268,2.128],[1.272,0.071],[0.022,0.278]],"v":[[33.512,52.81],[25.722,55.098],[-7.142,50.145],[-21.067,25.19],[-10.723,-4.696],[-1.066,-34.311],[-18.537,-50.389],[-30.097,-43.821],[-33.512,-39.871],[-22.74,-53.637],[9.419,-35.674],[5.193,1.564],[3.41,33.987],[16.059,47.988],[29.644,51.481],[33.445,51.975]],"c":true},"ix":2},"nm":"Trazado 1","mn":"ADBE Vector Shape - Group","hd":false},{"ty":"fl","c":{"a":0,"k":[0,0,0,1],"ix":4},"o":{"a":0,"k":100,"ix":5},"r":1,"bm":0,"nm":"Relleno 1","mn":"ADBE Vector Graphic - Fill","hd":false},{"ty":"tr","p":{"a":0,"k":[33.762,57.912],"ix":2},"a":{"a":0,"k":[0,0],"ix":1},"s":{"a":0,"k":[100,100],"ix":3},"r":{"a":0,"k":0,"ix":6},"o":{"a":0,"k":100,"ix":7},"sk":{"a":0,"k":0,"ix":4},"sa":{"a":0,"k":0,"ix":5},"nm":"Transformar"}],"nm":"Grupo 1","np":2,"cix":2,"bm":0,"ix":1,"mn":"ADBE Vector Group","hd":false}],"ip":0,"op":25,"st":0,"ct":1,"bm":0},{"ddd":0,"ind":8,"ty":4,"nm":"tentaculo 1 contornos","sr":1,"ks":{"o":{"a":0,"k":100,"ix":11},"r":{"a":1,"k":[{"i":{"x":[0.667],"y":[1]},"o":{"x":[0.333],"y":[0]},"t":0,"s":[0]},{"i":{"x":[0.667],"y":[1]},"o":{"x":[0.333],"y":[0]},"t":6,"s":[8]},{"i":{"x":[0.667],"y":[1]},"o":{"x":[0.333],"y":[0]},"t":12,"s":[0]},{"i":{"x":[0.667],"y":[1]},"o":{"x":[0.333],"y":[0]},"t":18,"s":[8]},{"t":24,"s":[0]}],"ix":10},"p":{"a":0,"k":[135.722,128.265,0],"ix":2,"l":2},"a":{"a":0,"k":[1.106,108.898,0],"ix":1,"l":2},"s":{"a":0,"k":[100,100,100],"ix":6,"l":2}},"ao":0,"shapes":[{"ty":"gr","it":[{"ind":0,"ty":"sh","ix":1,"ks":{"a":0,"k":{"i":[[-0.035,0.206],[-2.298,0.356],[-4.833,7.821],[-0.189,5.876],[2.593,6.701],[-1.123,11.025],[-14.625,-1.885],[-0.842,-7.65],[0.706,0.814],[5.984,0.133],[1.567,-7.698],[-3.599,-7.245],[-2.962,-5.153],[-0.152,-8.14],[15.234,-4.112],[10.124,3.729],[0.417,0.21]],"o":[[2.313,-0.258],[8.743,-1.355],[3.227,-5.223],[0.23,-7.14],[-3.957,-10.226],[1.724,-16.922],[7.097,0.915],[-0.67,-0.845],[-3.668,-4.229],[-7.813,-0.173],[-1.684,8.271],[2.637,5.308],[3.984,6.931],[0.219,11.663],[-10.467,2.825],[-0.435,-0.16],[0.035,-0.206]],"v":[[-33.251,51.604],[-26.314,50.816],[-5.268,38.109],[-1.545,21.083],[-5.398,0.424],[-10.122,-31.46],[19.899,-54.763],[33.356,-40.4],[31.342,-42.932],[17.564,-50.751],[1.685,-37.719],[5.558,-14.546],[14.635,0.799],[21.356,23.215],[-1.404,53.824],[-32.102,52.844],[-33.356,52.221]],"c":true},"ix":2},"nm":"Trazado 1","mn":"ADBE Vector Shape - Group","hd":false},{"ty":"fl","c":{"a":0,"k":[0,0,0,1],"ix":4},"o":{"a":0,"k":100,"ix":5},"r":1,"bm":0,"nm":"Relleno 1","mn":"ADBE Vector Graphic - Fill","hd":false},{"ty":"tr","p":{"a":0,"k":[33.606,56.899],"ix":2},"a":{"a":0,"k":[0,0],"ix":1},"s":{"a":0,"k":[100,100],"ix":3},"r":{"a":0,"k":0,"ix":6},"o":{"a":0,"k":100,"ix":7},"sk":{"a":0,"k":0,"ix":4},"sa":{"a":0,"k":0,"ix":5},"nm":"Transformar"}],"nm":"Grupo 1","np":2,"cix":2,"bm":0,"ix":1,"mn":"ADBE Vector Group","hd":false}],"ip":0,"op":25,"st":0,"ct":1,"bm":0},{"ddd":0,"ind":9,"ty":4,"nm":"Capa 1 contornos","sr":1,"ks":{"o":{"a":0,"k":100,"ix":11},"r":{"a":0,"k":0,"ix":10},"p":{"a":0,"k":[126.99,72.636,0],"ix":2,"l":2},"a":{"a":0,"k":[30.325,52.081,0],"ix":1,"l":2},"s":{"a":0,"k":[100,100,100],"ix":6,"l":2}},"ao":0,"shapes":[{"ty":"gr","it":[{"ind":0,"ty":"sh","ix":1,"ks":{"a":0,"k":{"i":[[-0.684,1.513],[0.689,-1.513]],"o":[[0.684,1.513],[-0.689,-1.513]],"v":[[0,-2.289],[0,2.289]],"c":true},"ix":2},"nm":"Trazado 1","mn":"ADBE Vector Shape - Group","hd":false},{"ty":"fl","c":{"a":0,"k":[0,0,0,1],"ix":4},"o":{"a":0,"k":100,"ix":5},"r":1,"bm":0,"nm":"Relleno 1","mn":"ADBE Vector Graphic - Fill","hd":false},{"ty":"tr","p":{"a":0,"k":[44.645,54.651],"ix":2},"a":{"a":0,"k":[0,0],"ix":1},"s":{"a":0,"k":[100,100],"ix":3},"r":{"a":0,"k":0,"ix":6},"o":{"a":0,"k":100,"ix":7},"sk":{"a":0,"k":0,"ix":4},"sa":{"a":0,"k":0,"ix":5},"nm":"Transformar"}],"nm":"Grupo 1","np":2,"cix":2,"bm":0,"ix":1,"mn":"ADBE Vector Group","hd":false},{"ty":"gr","it":[{"ind":0,"ty":"sh","ix":1,"ks":{"a":0,"k":{"i":[[0,0],[0,0]],"o":[[0,0],[0,0]],"v":[[44.645,52.363],[44.645,56.94]],"c":false},"ix":2},"nm":"Trazado 1","mn":"ADBE Vector Shape - Group","hd":false},{"ty":"fl","c":{"a":0,"k":[1,1,1,1],"ix":4},"o":{"a":0,"k":100,"ix":5},"r":1,"bm":0,"nm":"Relleno 1","mn":"ADBE Vector Graphic - Fill","hd":false},{"ty":"tr","p":{"a":0,"k":[0,0],"ix":2},"a":{"a":0,"k":[0,0],"ix":1},"s":{"a":0,"k":[100,100],"ix":3},"r":{"a":0,"k":0,"ix":6},"o":{"a":0,"k":100,"ix":7},"sk":{"a":0,"k":0,"ix":4},"sa":{"a":0,"k":0,"ix":5},"nm":"Transformar"}],"nm":"Grupo 2","np":2,"cix":2,"bm":0,"ix":2,"mn":"ADBE Vector Group","hd":false},{"ty":"gr","it":[{"ind":0,"ty":"sh","ix":1,"ks":{"a":0,"k":{"i":[[-0.684,1.513],[0.689,-1.513]],"o":[[0.684,1.513],[-0.689,-1.513]],"v":[[0,-2.289],[0,2.289]],"c":true},"ix":2},"nm":"Trazado 1","mn":"ADBE Vector Shape - Group","hd":false},{"ty":"fl","c":{"a":0,"k":[0,0,0,1],"ix":4},"o":{"a":0,"k":100,"ix":5},"r":1,"bm":0,"nm":"Relleno 1","mn":"ADBE Vector Graphic - Fill","hd":false},{"ty":"tr","p":{"a":0,"k":[15.658,54.651],"ix":2},"a":{"a":0,"k":[0,0],"ix":1},"s":{"a":0,"k":[100,100],"ix":3},"r":{"a":0,"k":0,"ix":6},"o":{"a":0,"k":100,"ix":7},"sk":{"a":0,"k":0,"ix":4},"sa":{"a":0,"k":0,"ix":5},"nm":"Transformar"}],"nm":"Grupo 3","np":2,"cix":2,"bm":0,"ix":3,"mn":"ADBE Vector Group","hd":false},{"ty":"gr","it":[{"ind":0,"ty":"sh","ix":1,"ks":{"a":0,"k":{"i":[[0,0],[0,0]],"o":[[0,0],[0,0]],"v":[[15.658,52.363],[15.658,56.94]],"c":false},"ix":2},"nm":"Trazado 1","mn":"ADBE Vector Shape - Group","hd":false},{"ty":"fl","c":{"a":0,"k":[1,1,1,1],"ix":4},"o":{"a":0,"k":100,"ix":5},"r":1,"bm":0,"nm":"Relleno 1","mn":"ADBE Vector Graphic - Fill","hd":false},{"ty":"tr","p":{"a":0,"k":[0,0],"ix":2},"a":{"a":0,"k":[0,0],"ix":1},"s":{"a":0,"k":[100,100],"ix":3},"r":{"a":0,"k":0,"ix":6},"o":{"a":0,"k":100,"ix":7},"sk":{"a":0,"k":0,"ix":4},"sa":{"a":0,"k":0,"ix":5},"nm":"Transformar"}],"nm":"Grupo 4","np":2,"cix":2,"bm":0,"ix":4,"mn":"ADBE Vector Group","hd":false},{"ty":"gr","it":[{"ind":0,"ty":"sh","ix":1,"ks":{"a":0,"k":{"i":[[-1.045,5.538],[-2.972,-2.555],[1.21,-3.942],[2.465,0.966]],"o":[[3.502,2.407],[2.383,2.049],[-1.446,-3.135],[-4.624,-1.812]],"v":[[-6.398,-7.883],[3.534,-0.932],[6.233,7.883],[-0.558,3.525]],"c":true},"ix":2},"nm":"Trazado 1","mn":"ADBE Vector Shape - Group","hd":false},{"ty":"st","c":{"a":0,"k":[1,1,1,1],"ix":3},"o":{"a":0,"k":100,"ix":4},"w":{"a":0,"k":1,"ix":5},"lc":1,"lj":1,"ml":10,"bm":0,"nm":"Trazo 1","mn":"ADBE Vector Graphic - Stroke","hd":false},{"ty":"fl","c":{"a":0,"k":[1,0,0,1],"ix":4},"o":{"a":0,"k":100,"ix":5},"r":1,"bm":0,"nm":"Relleno 1","mn":"ADBE Vector Graphic - Fill","hd":false},{"ty":"tr","p":{"a":0,"k":[15.925,54.474],"ix":2},"a":{"a":0,"k":[0,0],"ix":1},"s":{"a":0,"k":[100,100],"ix":3},"r":{"a":0,"k":0,"ix":6},"o":{"a":0,"k":100,"ix":7},"sk":{"a":0,"k":0,"ix":4},"sa":{"a":0,"k":0,"ix":5},"nm":"Transformar"}],"nm":"Grupo 5","np":3,"cix":2,"bm":0,"ix":5,"mn":"ADBE Vector Group","hd":false},{"ty":"gr","it":[{"ind":0,"ty":"sh","ix":1,"ks":{"a":0,"k":{"i":[[-2.458,1.414],[4.74,-1.821],[1.315,-3.09],[-0.787,1.629],[-2.319,1.482]],"o":[[1.043,5.232],[-2.381,0.915],[-0.706,-2.105],[1.2,-2.485],[2.261,-1.444]],"v":[[6.064,-7.785],[0.048,3.421],[-6.4,7.785],[-6.273,2.383],[-1.036,-3.671]],"c":true},"ix":2},"nm":"Trazado 1","mn":"ADBE Vector Shape - Group","hd":false},{"ty":"st","c":{"a":0,"k":[1,1,1,1],"ix":3},"o":{"a":0,"k":100,"ix":4},"w":{"a":0,"k":1,"ix":5},"lc":1,"lj":1,"ml":10,"bm":0,"nm":"Trazo 1","mn":"ADBE Vector Graphic - Stroke","hd":false},{"ty":"fl","c":{"a":0,"k":[1,0,0,1],"ix":4},"o":{"a":0,"k":100,"ix":5},"r":1,"bm":0,"nm":"Relleno 1","mn":"ADBE Vector Graphic - Fill","hd":false},{"ty":"tr","p":{"a":0,"k":[44.819,54.439],"ix":2},"a":{"a":0,"k":[0,0],"ix":1},"s":{"a":0,"k":[100,100],"ix":3},"r":{"a":0,"k":0,"ix":6},"o":{"a":0,"k":100,"ix":7},"sk":{"a":0,"k":0,"ix":4},"sa":{"a":0,"k":0,"ix":5},"nm":"Transformar"}],"nm":"Grupo 6","np":3,"cix":2,"bm":0,"ix":6,"mn":"ADBE Vector Group","hd":false},{"ty":"gr","it":[{"ind":0,"ty":"sh","ix":1,"ks":{"a":0,"k":{"i":[[-1.045,5.538],[-2.972,-2.555],[1.21,-3.942],[2.465,0.966]],"o":[[3.502,2.407],[2.383,2.049],[-1.446,-3.135],[-4.624,-1.812]],"v":[[-6.398,-7.883],[3.534,-0.932],[6.233,7.883],[-0.558,3.525]],"c":true},"ix":2},"nm":"Trazado 1","mn":"ADBE Vector Shape - Group","hd":false},{"ty":"st","c":{"a":0,"k":[1,1,1,1],"ix":3},"o":{"a":0,"k":100,"ix":4},"w":{"a":0,"k":1,"ix":5},"lc":1,"lj":1,"ml":10,"bm":0,"nm":"Trazo 1","mn":"ADBE Vector Graphic - Stroke","hd":false},{"ty":"tr","p":{"a":0,"k":[15.925,54.474],"ix":2},"a":{"a":0,"k":[0,0],"ix":1},"s":{"a":0,"k":[100,100],"ix":3},"r":{"a":0,"k":0,"ix":6},"o":{"a":0,"k":100,"ix":7},"sk":{"a":0,"k":0,"ix":4},"sa":{"a":0,"k":0,"ix":5},"nm":"Transformar"}],"nm":"Grupo 7","np":2,"cix":2,"bm":0,"ix":7,"mn":"ADBE Vector Group","hd":false},{"ty":"gr","it":[{"ind":0,"ty":"sh","ix":1,"ks":{"a":0,"k":{"i":[[-2.458,1.414],[4.74,-1.821],[1.315,-3.09],[-0.787,1.629],[-2.319,1.482]],"o":[[1.043,5.232],[-2.381,0.915],[-0.706,-2.105],[1.2,-2.485],[2.261,-1.444]],"v":[[6.064,-7.785],[0.048,3.421],[-6.4,7.785],[-6.273,2.383],[-1.036,-3.671]],"c":true},"ix":2},"nm":"Trazado 1","mn":"ADBE Vector Shape - Group","hd":false},{"ty":"st","c":{"a":0,"k":[1,1,1,1],"ix":3},"o":{"a":0,"k":100,"ix":4},"w":{"a":0,"k":1,"ix":5},"lc":1,"lj":1,"ml":10,"bm":0,"nm":"Trazo 1","mn":"ADBE Vector Graphic - Stroke","hd":false},{"ty":"tr","p":{"a":0,"k":[44.819,54.439],"ix":2},"a":{"a":0,"k":[0,0],"ix":1},"s":{"a":0,"k":[100,100],"ix":3},"r":{"a":0,"k":0,"ix":6},"o":{"a":0,"k":100,"ix":7},"sk":{"a":0,"k":0,"ix":4},"sa":{"a":0,"k":0,"ix":5},"nm":"Transformar"}],"nm":"Grupo 8","np":2,"cix":2,"bm":0,"ix":8,"mn":"ADBE Vector Group","hd":false},{"ty":"gr","it":[{"ind":0,"ty":"sh","ix":1,"ks":{"a":0,"k":{"i":[[0.152,0.157],[-6.015,2.217],[-2.564,-2.269],[0.832,-3.119],[4.756,-1.376],[2.484,0.081],[-1.131,0.796],[-1.095,1.924],[0.864,1.533],[1.327,-0.328],[2.623,-1.231],[0.955,-0.662]],"o":[[3.943,-4.612],[3.277,-1.208],[2.728,2.414],[-1.402,5.25],[-2.223,0.643],[1.281,-0.582],[1.933,-1.362],[0.786,-1.379],[-0.573,-1.017],[-2.777,0.686],[-1.038,0.487],[-0.153,-0.157]],"v":[[-12.635,2.027],[1.238,-9.415],[9.841,-7.729],[11.803,0.842],[1.464,9.723],[-5.577,10.542],[-1.76,8.757],[3.583,4.18],[3.076,-1.383],[-1.288,-2.785],[-9.299,0.538],[-12.179,2.497]],"c":true},"ix":2},"nm":"Trazado 1","mn":"ADBE Vector Shape - Group","hd":false},{"ty":"fl","c":{"a":0,"k":[0,0,0,1],"ix":4},"o":{"a":0,"k":100,"ix":5},"r":1,"bm":0,"nm":"Relleno 1","mn":"ADBE Vector Graphic - Fill","hd":false},{"ty":"tr","p":{"a":0,"k":[47.764,93.257],"ix":2},"a":{"a":0,"k":[0,0],"ix":1},"s":{"a":0,"k":[100,100],"ix":3},"r":{"a":0,"k":0,"ix":6},"o":{"a":0,"k":100,"ix":7},"sk":{"a":0,"k":0,"ix":4},"sa":{"a":0,"k":0,"ix":5},"nm":"Transformar"}],"nm":"Grupo 9","np":2,"cix":2,"bm":0,"ix":9,"mn":"ADBE Vector Group","hd":false},{"ty":"gr","it":[{"ind":0,"ty":"sh","ix":1,"ks":{"a":0,"k":{"i":[[-2.755,-4.5],[2.263,1.204],[1.301,0.248],[1.146,-2.272],[-2.088,-1.624],[-1.897,-1.04],[-0.663,-0.538],[4.055,4.053],[-2.212,2.869],[-5.232,-2.889]],"o":[[-2.195,-1.332],[-1.157,-0.616],[-2.199,-0.418],[-1.194,2.364],[1.689,1.314],[0.712,0.391],[-5.439,-0.265],[-3.147,-3.146],[3.126,-4.057],[4.524,2.499]],"v":[[12.677,2.631],[6.072,-1.328],[2.273,-2.543],[-3.111,-0.391],[-1.817,6.489],[3.792,9.735],[5.939,10.945],[-8.772,5.676],[-10.465,-6.135],[1.861,-8.056]],"c":true},"ix":2},"nm":"Trazado 1","mn":"ADBE Vector Shape - Group","hd":false},{"ty":"fl","c":{"a":0,"k":[0,0,0,1],"ix":4},"o":{"a":0,"k":100,"ix":5},"r":1,"bm":0,"nm":"Relleno 1","mn":"ADBE Vector Graphic - Fill","hd":false},{"ty":"tr","p":{"a":0,"k":[12.927,92.967],"ix":2},"a":{"a":0,"k":[0,0],"ix":1},"s":{"a":0,"k":[100,100],"ix":3},"r":{"a":0,"k":0,"ix":6},"o":{"a":0,"k":100,"ix":7},"sk":{"a":0,"k":0,"ix":4},"sa":{"a":0,"k":0,"ix":5},"nm":"Transformar"}],"nm":"Grupo 10","np":2,"cix":2,"bm":0,"ix":10,"mn":"ADBE Vector Group","hd":false},{"ty":"gr","it":[{"ind":0,"ty":"sh","ix":1,"ks":{"a":0,"k":{"i":[[0,1.767],[-8.638,10.748],[-4.055,3.614],[-2.29,-1.468],[-3.59,-11.598],[1.064,-10.373],[3.579,-4.81],[7.372,-5.346],[0.445,0.337],[4.506,10.498],[0.834,5.366]],"o":[[-0.11,-13.523],[3.362,-4.183],[2.054,-1.83],[10.371,6.647],[3.112,10.055],[-0.587,5.73],[-5.47,7.352],[-0.52,0.377],[-8.855,-6.713],[-2.085,-4.86],[-0.268,-1.726]],"v":[[-26.544,2.167],[-15.302,-34.91],[-3.35,-45.956],[3.047,-46.035],[23.535,-18.326],[25.706,12.406],[20.575,28.508],[1.049,47.27],[-1.127,47.448],[-23.505,23.429],[-26.502,7.463]],"c":true},"ix":2},"nm":"Trazado 1","mn":"ADBE Vector Shape - Group","hd":false},{"ty":"fl","c":{"a":0,"k":[0,0,0,1],"ix":4},"o":{"a":0,"k":100,"ix":5},"r":1,"bm":0,"nm":"Relleno 1","mn":"ADBE Vector Graphic - Fill","hd":false},{"ty":"tr","p":{"a":0,"k":[30.781,48.036],"ix":2},"a":{"a":0,"k":[0,0],"ix":1},"s":{"a":0,"k":[100,100],"ix":3},"r":{"a":0,"k":0,"ix":6},"o":{"a":0,"k":100,"ix":7},"sk":{"a":0,"k":0,"ix":4},"sa":{"a":0,"k":0,"ix":5},"nm":"Transformar"}],"nm":"Grupo 11","np":2,"cix":2,"bm":0,"ix":11,"mn":"ADBE Vector Group","hd":false}],"ip":0,"op":25,"st":0,"ct":1,"bm":0}],"markers":[],"props":{}}